MANIFEST.in
README.md
pyproject.toml
setup.cfg
setup.py
src/stochastic_relaxation/__init__.py
src/stochastic_relaxation/baoab.py
src/stochastic_relaxation/hours.py
src/stochastic_relaxation/ovrvo.py
src/stochastic_relaxation.egg-info/PKG-INFO
src/stochastic_relaxation.egg-info/SOURCES.txt
src/stochastic_relaxation.egg-info/dependency_links.txt
src/stochastic_relaxation.egg-info/requires.txt
src/stochastic_relaxation.egg-info/top_level.txt
src/stochastic_relaxation/util/__init__.py
src/stochastic_relaxation/util/constants.py
src/stochastic_relaxation/util/data.py
src/stochastic_relaxation/util/force.py
src/stochastic_relaxation/util/integrator.py
src/stochastic_relaxation/util/options.py
src/stochastic_relaxation/util/random.py
src/stochastic_relaxation/util/units.py